.editorconfig
.gitignore
Makefile
README.md
deploy_latest.sh
requirements.txt
setup.py
cvargparse/__init__.py
cvargparse/_version.py
cvargparse/argument.py
cvargparse/factory.py
cvargparse.egg-info/PKG-INFO
cvargparse.egg-info/SOURCES.txt
cvargparse.egg-info/dependency_links.txt
cvargparse.egg-info/not-zip-safe
cvargparse.egg-info/requires.txt
cvargparse.egg-info/top_level.txt
cvargparse/parser/__init__.py
cvargparse/parser/base.py
cvargparse/parser/gpu_parser.py
cvargparse/parser/mode_parser.py
cvargparse/utils/__init__.py
cvargparse/utils/dataclass.py
cvargparse/utils/decorators.py
cvargparse/utils/enumerations.py
cvargparse/utils/logger_config.py