Metadata-Version: 2.1
Name: cvargparse
Version: 0.5.4
Summary: simple argparse wrapper with some syntactic sugar
Home-page: UNKNOWN
Author: Dimitri Korsch, Christoph Theiß
Author-email: korschdima@gmail.com, theisz.cm@gmail.com
License: MIT License
Platform: UNKNOWN
